biot_python_sdk/BioT_API_URLS.py
biot_python_sdk/__init__.py
biot_python_sdk/biot.py
biot_python_sdk/logger.py
biot_python_sdk/multipart.py
biot_python_sdk-1.0.20.dist-info/LICENSE
biot_python_sdk-1.0.20.dist-info/METADATA
biot_python_sdk-1.0.20.dist-info/WHEEL
biot_python_sdk-1.0.20.dist-info/top_level.txt
biot_python_sdk-1.0.20.dist-info/RECORD
