Metadata-Version: 2.1
Name: biot-python-sdk
Version: 1.0.20
Summary: A python SDK that wraps Bio-T Open API
Home-page: https://github.com/sstbrg/biot_python_sdk
Author: Stanislav Steinberg
Author-email: sstbrg@gmail.com
License-File: LICENSE
Requires-Dist: pytest==8.3.4
Requires-Dist: Requests==2.32.3
Requires-Dist: setuptools==68.1.2
